{
    "key": "group_676ec48b46c9c",
    "title": "Cards Info",
    "fields": [
        {
            "key": "field_676ec48b4856c",
            "label": "Cards Info",
            "name": "content_block_cards",
            "aria-label": "",
            "type": "group",
            "instructions": "",
            "required": 0,
            "conditional_logic": 0,
            "wrapper": {
                "width": "",
                "class": "",
                "id": ""
            },
            "layout": "block",
            "sub_fields": [
                {
                    "key": "field_676ec48b491a7",
                    "label": "Info List",
                    "name": "info_list",
                    "aria-label": "",
                    "type": "repeater",
                    "instructions": "",
                    "required": 0,
                    "conditional_logic": 0,
                    "wrapper": {
                        "width": "",
                        "class": "",
                        "id": ""
                    },
                    "layout": "row",
                    "pagination": 0,
                    "min": 0,
                    "max": 0,
                    "collapsed": "",
                    "button_label": "Add Card",
                    "rows_per_page": 20,
                    "sub_fields": [
                        {
                            "key": "field_676ec48b4a75e",
                            "label": "Heading",
                            "name": "heading",
                            "aria-label": "",
                            "type": "text",
                            "instructions": "",
                            "required": 0,
                            "conditional_logic": 0,
                            "wrapper": {
                                "width": "",
                                "class": "",
                                "id": ""
                            },
                            "default_value": "",
                            "maxlength": "",
                            "placeholder": "",
                            "prepend": "",
                            "append": "",
                            "parent_repeater": "field_676ec48b491a7"
                        },
                        {
                            "key": "field_676ec48b4a768",
                            "label": "Description",
                            "name": "description",
                            "aria-label": "",
                            "type": "wysiwyg",
                            "instructions": "",
                            "required": 0,
                            "conditional_logic": 0,
                            "wrapper": {
                                "width": "",
                                "class": "",
                                "id": ""
                            },
                            "default_value": "",
                            "allow_in_bindings": 1,
                            "tabs": "all",
                            "toolbar": "full",
                            "media_upload": 1,
                            "delay": 0,
                            "parent_repeater": "field_676ec48b491a7"
                        },
                        {
                            "key": "field_676ec48b4a761",
                            "label": "Image",
                            "name": "image",
                            "aria-label": "",
                            "type": "image",
                            "instructions": "",
                            "required": 0,
                            "conditional_logic": 0,
                            "wrapper": {
                                "width": "",
                                "class": "",
                                "id": ""
                            },
                            "return_format": "array",
                            "library": "all",
                            "min_width": "",
                            "min_height": "",
                            "min_size": "",
                            "max_width": "",
                            "max_height": "",
                            "max_size": "",
                            "mime_types": "",
                            "allow_in_bindings": 1,
                            "preview_size": "medium",
                            "parent_repeater": "field_676ec48b491a7"
                        }
                    ]
                },
                {
                    "key": "field_676ec48b491ab",
                    "label": "Spacing",
                    "name": "spacing",
                    "aria-label": "",
                    "type": "button_group",
                    "instructions": "",
                    "required": 0,
                    "conditional_logic": 0,
                    "wrapper": {
                        "width": "50",
                        "class": "",
                        "id": ""
                    },
                    "choices": {
                        "small": "Small",
                        "medium": "Medium",
                        "large": "Large"
                    },
                    "default_value": "small",
                    "return_format": "value",
                    "allow_null": 0,
                    "allow_in_bindings": 1,
                    "layout": "horizontal"
                },
                {
                    "key": "field_676ec48b491ae",
                    "label": "Spacing Top Desktop?",
                    "name": "spacing_top_desktop",
                    "aria-label": "",
                    "type": "true_false",
                    "instructions": "",
                    "required": 0,
                    "conditional_logic": 0,
                    "wrapper": {
                        "width": "20",
                        "class": "",
                        "id": ""
                    },
                    "message": "",
                    "default_value": 0,
                    "allow_in_bindings": 1,
                    "ui_on_text": "",
                    "ui_off_text": "",
                    "ui": 1
                },
                {
                    "key": "field_676ec48b491b1",
                    "label": "Spacing Bottom Desktop",
                    "name": "spacing_bottom_desktop",
                    "aria-label": "",
                    "type": "true_false",
                    "instructions": "",
                    "required": 0,
                    "conditional_logic": 0,
                    "wrapper": {
                        "width": "20",
                        "class": "",
                        "id": ""
                    },
                    "message": "",
                    "default_value": 0,
                    "allow_in_bindings": 1,
                    "ui_on_text": "",
                    "ui_off_text": "",
                    "ui": 1
                },
                {
                    "key": "field_676ec48b491b4",
                    "label": "Spacing Top Mobile",
                    "name": "spacing_top_mobile",
                    "aria-label": "",
                    "type": "true_false",
                    "instructions": "",
                    "required": 0,
                    "conditional_logic": 0,
                    "wrapper": {
                        "width": "20",
                        "class": "",
                        "id": ""
                    },
                    "message": "",
                    "default_value": 0,
                    "allow_in_bindings": 1,
                    "ui_on_text": "",
                    "ui_off_text": "",
                    "ui": 1
                },
                {
                    "key": "field_676ec48b491b7",
                    "label": "Spacing Bottom Mobile",
                    "name": "spacing_bottom_mobile",
                    "aria-label": "",
                    "type": "true_false",
                    "instructions": "",
                    "required": 0,
                    "conditional_logic": 0,
                    "wrapper": {
                        "width": "20",
                        "class": "",
                        "id": ""
                    },
                    "message": "",
                    "default_value": 0,
                    "allow_in_bindings": 1,
                    "ui_on_text": "",
                    "ui_off_text": "",
                    "ui": 1
                }
            ]
        }
    ],
    "location": [
        [
            {
                "param": "block",
                "operator": "==",
                "value": "acf\/cards-info"
            }
        ]
    ],
    "menu_order": 0,
    "position": "normal",
    "style": "default",
    "label_placement": "top",
    "instruction_placement": "label",
    "hide_on_screen": "",
    "active": true,
    "description": "",
    "show_in_rest": 0,
    "modified": 1735312746
}
